sommer/__init__.py
sommer-0.0.1.dist-info/METADATA
sommer-0.0.1.dist-info/WHEEL
sommer-0.0.1.dist-info/top_level.txt
sommer-0.0.1.dist-info/RECORD
